autodiffcc/ADmath.py
autodiffcc/__init__.py
autodiffcc/core.py
autodiffcc/parser.py
autodiffcc/root.py
autodiffcc/Equation/__init__.py
autodiffcc/Equation/_info.py
autodiffcc/Equation/core.py
autodiffcc/Equation/equation_base.py
autodiffcc/Equation/equation_scipy.py
autodiffcc/Equation/similar.py
autodiffcc/Equation/util.py
tests/__init__.py
tests/test_ADmath.py
tests/test_core.py
tests/test_parser.py
tests/test_root.py
AutoDiffCC-1.1.1.dist-info/METADATA
AutoDiffCC-1.1.1.dist-info/WHEEL
AutoDiffCC-1.1.1.dist-info/top_level.txt
AutoDiffCC-1.1.1.dist-info/RECORD
