Metadata-Version: 2.1
Name: AutoDiffCC
Version: 1.1.1
Summary: An AutoDifferentiation Library
Home-page: https://github.com/Crimson-Computing/cs207-FinalProject
Author: Crimson Computing
Author-email: majagarbulinska@hsph.harvard.edu
License: UNKNOWN
Platform: UNKNOWN
Classifier: Programming Language :: Python :: 3
Classifier: License :: OSI Approved :: MIT License
Classifier: Operating System :: OS Independent
Requires-Python: >=3.6
